google_play_api.py
gplay.py
gplay-1.0.5.dist-info/DESCRIPTION.rst
gplay-1.0.5.dist-info/METADATA
gplay-1.0.5.dist-info/RECORD
gplay-1.0.5.dist-info/WHEEL
gplay-1.0.5.dist-info/entry_points.txt
gplay-1.0.5.dist-info/metadata.json
gplay-1.0.5.dist-info/top_level.txt
