Metadata-Version: 2.0
Name: gplay
Version: 1.0.5
Summary: A Google Play Api Command Line Interface (CLI)
Home-page: https://github.com/nassendelft/google-play-cli
Author: Nick Assendelft
Author-email: n.assendelft@gmail.com
License: GPL-3.0
Keywords: cli command-line google google-api api play google-play
Platform: UNKNOWN
Classifier: Development Status :: 4 - Beta
Classifier: Intended Audience :: Developers
Classifier: Topic :: Utilities
Classifier: License :: OSI Approved :: GNU General Public License v3 (GPLv3)
Classifier: Programming Language :: Python :: 2.6
Classifier: Programming Language :: Python :: 2.7
Classifier: Programming Language :: Python :: 3
Classifier: Programming Language :: Python :: 3.3
Classifier: Programming Language :: Python :: 3.4
Classifier: Programming Language :: Python :: 3.5
Requires-Dist: docopt
Requires-Dist: google-api-python-client
